MANIFEST.in
README.rst
setup.cfg
setup.py
docs/HISTORY.rst
vs/__init__.py
vs.zopeskel.diazo.egg-info/PKG-INFO
vs.zopeskel.diazo.egg-info/SOURCES.txt
vs.zopeskel.diazo.egg-info/dependency_links.txt
vs.zopeskel.diazo.egg-info/entry_points.txt
vs.zopeskel.diazo.egg-info/namespace_packages.txt
vs.zopeskel.diazo.egg-info/not-zip-safe
vs.zopeskel.diazo.egg-info/requires.txt
vs.zopeskel.diazo.egg-info/top_level.txt
vs/zopeskel/__init__.py
vs/zopeskel/diazo/__init__.py
vs/zopeskel/diazo/diazo.py
vs/zopeskel/diazo/templates/bootstrap/bootstrap.py
vs/zopeskel/diazo/templates/bootstrap/buildout.cfg_tmpl
vs/zopeskel/diazo/templates/bootstrap/setup.cfg
vs/zopeskel/diazo/templates/bootstrap/setup.py_tmpl
vs/zopeskel/diazo/templates/bootstrap/+namespace_package+/+package+/Gruntfile.js
vs/zopeskel/diazo/templates/bootstrap/+namespace_package+/+package+/bower.json_tmpl
vs/zopeskel/diazo/templates/bootstrap/+namespace_package+/+package+/configure.zcml_tmpl
vs/zopeskel/diazo/templates/bootstrap/+namespace_package+/+package+/interfaces.py
vs/zopeskel/diazo/templates/bootstrap/+namespace_package+/+package+/package.json_tmpl
vs/zopeskel/diazo/templates/bootstrap/+namespace_package+/+package+/version.txt_tmpl
vs/zopeskel/diazo/templates/bootstrap/+namespace_package+/+package+/js/require.js
vs/zopeskel/diazo/templates/bootstrap/+namespace_package+/+package+/less/custom.less
vs/zopeskel/diazo/templates/bootstrap/+namespace_package+/+package+/locales/README.rst_tmpl
vs/zopeskel/diazo/templates/bootstrap/+namespace_package+/+package+/overrides/README.rst_tmpl
vs/zopeskel/diazo/templates/bootstrap/+namespace_package+/+package+/profiles/default/browserlayer.xml_tmpl
vs/zopeskel/diazo/templates/bootstrap/+namespace_package+/+package+/profiles/default/cssregistry.xml_tmpl
vs/zopeskel/diazo/templates/bootstrap/+namespace_package+/+package+/profiles/default/jsregistry.xml_tmpl
vs/zopeskel/diazo/templates/bootstrap/+namespace_package+/+package+/profiles/default/metadata.xml_tmpl
vs/zopeskel/diazo/templates/bootstrap/+namespace_package+/+package+/profiles/default/theme.xml_tmpl
vs/zopeskel/diazo/templates/bootstrap/+namespace_package+/+package+/theme/favicon.ico
vs/zopeskel/diazo/templates/bootstrap/+namespace_package+/+package+/theme/index.html
