Metadata-Version: 1.1
Name: vs.zopeskel.diazo
Version: 1.0
Summary: Paster templates for Plone Diazo theme package
Home-page: http://github.com/veit/vs.zopeskel.diazo
Author: Veit Schiele
Author-email: kontakt@veit-schiele.de
License: GPL 2
Keywords: plone zope diazo bootstrap
Platform: UNKNOWN
Classifier: Programming Language :: Python
Classifier: Framework :: Plone
Classifier: Framework :: Zope3
Classifier: Topic :: Software Development :: Libraries :: Python Modules
